<customapi uniquename="cat_Echo">
  <allowedcustomprocessingsteptype>0</allowedcustomprocessingsteptype>
  <bindingtype>0</bindingtype>
  <description default="cat_Echo">
    <label description="cat_Echo" languagecode="1033" />
  </description>
  <displayname default="cat_Echo">
    <label description="cat_Echo" languagecode="1033" />
  </displayname>
  <iscustomizable>1</iscustomizable>
  <isfunction>0</isfunction>
  <isprivate>0</isprivate>
  <name>cat_Echo</name>
  <plugintypeid>
    <plugintypeid>19cf165e-9d30-436b-85d4-7adc8ac23c51</plugintypeid>
  </plugintypeid>
  <workflowsdkstepenabled>0</workflowsdkstepenabled>
</customapi>